LICENSE
MANIFEST.in
README.rst
README.ru.rst
setup.py
django_tilda.egg-info/PKG-INFO
django_tilda.egg-info/SOURCES.txt
django_tilda.egg-info/dependency_links.txt
django_tilda.egg-info/pbr.json
django_tilda.egg-info/requires.txt
django_tilda.egg-info/top_level.txt
tilda/__init__.py
tilda/admin.py
tilda/api.py
tilda/fields.py
tilda/helpers.py
tilda/models.py
tilda/locale/ru/LC_MESSAGES/django.mo
tilda/locale/ru/LC_MESSAGES/django.po
tilda/migrations/0001_initial.py
tilda/migrations/__init__.py
tilda/templates/tilda/widget.html