Metadata-Version: 1.1
Name: django-tilda
Version: 1.0.4
Summary: A Django app for fetch/download pages from API Tilda.cc
Home-page: https://github.com/1vank1n/django-tilda
Author: Ivan Lukyanets
Author-email: lukyanets.ivan@gmail.com
License: MIT
Keywords: django tilda
Platform: UNKNOWN
Classifier: Development Status :: 4 - Beta
Classifier: Framework :: Django
Classifier: Intended Audience :: Developers
Classifier: License :: OSI Approved :: MIT License
Classifier: Operating System :: OS Independent
Classifier: Programming Language :: Python :: 3
Classifier: Programming Language :: Python :: 3.3
Classifier: Programming Language :: Python :: 3.4
Classifier: Programming Language :: Python :: 3.6
